netexp/__init__.py
netexp/helpers.py
netexp/pcap.py
netexp/throughput.py
netexp/pktgen/__init__.py
netexp/pktgen/dpdk.py
netexp/pktgen/enso.py
netexp/pktgen/norman.py
netexp/pktgen/zhipeng_fpga.py
netexp-0.2.0.dist-info/LICENSE
netexp-0.2.0.dist-info/METADATA
netexp-0.2.0.dist-info/WHEEL
netexp-0.2.0.dist-info/top_level.txt
netexp-0.2.0.dist-info/RECORD
