Metadata-Version: 2.1
Name: netexp
Version: 0.2.0
Summary: Python library to automate network experiments.
Home-page: https://github.com/hsadok/netexp
Download-URL: https://github.com/hsadok/netexp
Author: Hugo Sadok
Author-email: sadok@cmu.edu
License: BSD
Keywords: network,experiment,automation
Classifier: Development Status :: 4 - Beta
Classifier: Intended Audience :: Science/Research
Classifier: License :: OSI Approved :: BSD License
Classifier: Natural Language :: English
Classifier: Programming Language :: Python
Classifier: Programming Language :: Python :: 3.9
Classifier: Programming Language :: Python :: 3.10
Classifier: Topic :: Scientific/Engineering :: Visualization
Classifier: Topic :: System :: Installation/Setup 
Classifier: Topic :: System :: Networking
Classifier: Topic :: System :: Systems Administration
Requires-Python: >=3.9
License-File: LICENSE
Requires-Dist: paramiko
Requires-Dist: cffi
